{
    "asset": {
        "format": "jpg",
        "id": "1cbcecc1df2e90e823215582109ad8ae",
        "name": "efa71495-ido_56_jpg.rf.c89c06a1392afa0faeee509212d6b377.jpg",
        "path": "file:C:/Dev/ml.net/coins/efa71495-ido_56_jpg.rf.c89c06a1392afa0faeee509212d6b377.jpg",
        "size": {
            "width": 640,
            "height": 640
        },
        "state": 2,
        "type": 1
    },
    "regions": [
        {
            "id": "90acFWWLMl",
            "type": "RECTANGLE",
            "tags": [
                "10"
            ],
            "boundingBox": {
                "height": 54.85711495535714,
                "width": 59.245703125,
                "left": 164.93716517857143,
                "top": 355.47430245535713
            },
            "points": [
                {
                    "x": 164.93716517857143,
                    "y": 355.47430245535713
                },
                {
                    "x": 224.1828683035714,
                    "y": 355.47430245535713
                },
                {
                    "x": 224.1828683035714,
                    "y": 410.33141741071427
                },
                {
                    "x": 164.93716517857143,
                    "y": 410.33141741071427
                }
            ]
        },
        {
            "id": "8ol1PUyDWu",
            "type": "RECTANGLE",
            "tags": [
                "10"
            ],
            "boundingBox": {
                "height": 49.00571986607142,
                "width": 62.17142857142857,
                "left": 351.4514508928571,
                "top": 241.37142857142857
            },
            "points": [
                {
                    "x": 351.4514508928571,
                    "y": 241.37142857142857
                },
                {
                    "x": 413.6228794642857,
                    "y": 241.37142857142857
                },
                {
                    "x": 413.6228794642857,
                    "y": 290.3771484375
                },
                {
                    "x": 351.4514508928571,
                    "y": 290.3771484375
                }
            ]
        },
        {
            "id": "qonpzpTvY2",
            "type": "RECTANGLE",
            "tags": [
                "10"
            ],
            "boundingBox": {
                "height": 55.58857421875,
                "width": 58.51428571428571,
                "left": 200.77717633928572,
                "top": 115.56572265625
            },
            "points": [
                {
                    "x": 200.77717633928572,
                    "y": 115.56572265625
                },
                {
                    "x": 259.2914620535714,
                    "y": 115.56572265625
                },
                {
                    "x": 259.2914620535714,
                    "y": 171.154296875
                },
                {
                    "x": 200.77717633928572,
                    "y": 171.154296875
                }
            ]
        },
        {
            "id": "iIz2R9A4AI",
            "type": "RECTANGLE",
            "tags": [
                "1"
            ],
            "boundingBox": {
                "height": 45.348563058035715,
                "width": 51.199999999999996,
                "left": 145.92003348214286,
                "top": 78.99429408482142
            },
            "points": [
                {
                    "x": 145.92003348214286,
                    "y": 78.99429408482142
                },
                {
                    "x": 197.12003348214284,
                    "y": 78.99429408482142
                },
                {
                    "x": 197.12003348214284,
                    "y": 124.34285714285714
                },
                {
                    "x": 145.92003348214286,
                    "y": 124.34285714285714
                }
            ]
        },
        {
            "id": "ateLBzgJ4j",
            "type": "RECTANGLE",
            "tags": [
                "1"
            ],
            "boundingBox": {
                "height": 53.39428013392857,
                "width": 47.542857142857144,
                "left": 314.88002232142856,
                "top": 92.16000279017857
            },
            "points": [
                {
                    "x": 314.88002232142856,
                    "y": 92.16000279017857
                },
                {
                    "x": 362.4228794642857,
                    "y": 92.16000279017857
                },
                {
                    "x": 362.4228794642857,
                    "y": 145.55428292410713
                },
                {
                    "x": 314.88002232142856,
                    "y": 145.55428292410713
                }
            ]
        },
        {
            "id": "aL-DVKpNfX",
            "type": "RECTANGLE",
            "tags": [
                "5"
            ],
            "boundingBox": {
                "height": 55.588588169642854,
                "width": 62.17142857142857,
                "left": 275.3828683035714,
                "top": 375.2228515625
            },
            "points": [
                {
                    "x": 275.3828683035714,
                    "y": 375.2228515625
                },
                {
                    "x": 337.554296875,
                    "y": 375.2228515625
                },
                {
                    "x": 337.554296875,
                    "y": 430.81143973214284
                },
                {
                    "x": 275.3828683035714,
                    "y": 430.81143973214284
                }
            ]
        },
        {
            "id": "Ej0vu8ncXg",
            "type": "RECTANGLE",
            "tags": [
                "1"
            ],
            "boundingBox": {
                "height": 41.69140625,
                "width": 49.00569196428571,
                "left": 325.85145089285714,
                "top": 415.4514508928571
            },
            "points": [
                {
                    "x": 325.85145089285714,
                    "y": 415.4514508928571
                },
                {
                    "x": 374.85714285714283,
                    "y": 415.4514508928571
                },
                {
                    "x": 374.85714285714283,
                    "y": 457.1428571428571
                },
                {
                    "x": 325.85145089285714,
                    "y": 457.1428571428571
                }
            ]
        },
        {
            "id": "6_qP246paL",
            "type": "RECTANGLE",
            "tags": [
                "1"
            ],
            "boundingBox": {
                "height": 44.61713169642857,
                "width": 47.54280133928571,
                "left": 497.00574776785714,
                "top": 405.2114397321428
            },
            "points": [
                {
                    "x": 497.00574776785714,
                    "y": 405.2114397321428
                },
                {
                    "x": 544.5485491071429,
                    "y": 405.2114397321428
                },
                {
                    "x": 544.5485491071429,
                    "y": 449.8285714285714
                },
                {
                    "x": 497.00574776785714,
                    "y": 449.8285714285714
                }
            ]
        },
        {
            "id": "ZAB3gGqbNk",
            "type": "RECTANGLE",
            "tags": [
                "1"
            ],
            "boundingBox": {
                "height": 54.125697544642854,
                "width": 62.17142857142857,
                "left": 543.0857142857143,
                "top": 374.4914341517857
            },
            "points": [
                {
                    "x": 543.0857142857143,
                    "y": 374.4914341517857
                },
                {
                    "x": 605.2571428571429,
                    "y": 374.4914341517857
                },
                {
                    "x": 605.2571428571429,
                    "y": 428.61713169642854
                },
                {
                    "x": 543.0857142857143,
                    "y": 428.61713169642854
                }
            ]
        }
    ],
    "version": "2.2.0"
}