{
    "asset": {
        "format": "jpg",
        "id": "ff5871a1e133a2bf395cdab7e6ad1f48",
        "name": "IMG_3089_JPG.rf.21757501b9d283432964a3f70cbfd51c.jpg",
        "path": "file:C:/Dev/ml.net/coins/IMG_3089_JPG.rf.21757501b9d283432964a3f70cbfd51c.jpg",
        "size": {
            "width": 640,
            "height": 640
        },
        "state": 2,
        "type": 1
    },
    "regions": [
        {
            "id": "TIbtUbpQTa",
            "type": "RECTANGLE",
            "tags": [
                "1"
            ],
            "boundingBox": {
                "height": 75.337109375,
                "width": 105.32566964285714,
                "left": 241.00574776785714,
                "top": 422.03431919642856
            },
            "points": [
                {
                    "x": 241.00574776785714,
                    "y": 422.03431919642856
                },
                {
                    "x": 346.33141741071427,
                    "y": 422.03431919642856
                },
                {
                    "x": 346.33141741071427,
                    "y": 497.37142857142857
                },
                {
                    "x": 241.00574776785714,
                    "y": 497.37142857142857
                }
            ]
        },
        {
            "id": "JN6vnH-Whu",
            "type": "RECTANGLE",
            "tags": [
                "10"
            ],
            "boundingBox": {
                "height": 80.45714285714286,
                "width": 116.29715401785714,
                "left": 328.045703125,
                "top": 421.30284598214286
            },
            "points": [
                {
                    "x": 328.045703125,
                    "y": 421.30284598214286
                },
                {
                    "x": 444.34285714285716,
                    "y": 421.30284598214286
                },
                {
                    "x": 444.34285714285716,
                    "y": 501.7599888392857
                },
                {
                    "x": 328.045703125,
                    "y": 501.7599888392857
                }
            ]
        },
        {
            "id": "mU38ASLB-a",
            "type": "RECTANGLE",
            "tags": [
                "1"
            ],
            "boundingBox": {
                "height": 65.82857142857142,
                "width": 116.29715401785714,
                "left": 258.5599888392857,
                "top": 506.14860491071425
            },
            "points": [
                {
                    "x": 258.5599888392857,
                    "y": 506.14860491071425
                },
                {
                    "x": 374.85714285714283,
                    "y": 506.14860491071425
                },
                {
                    "x": 374.85714285714283,
                    "y": 571.9771763392857
                },
                {
                    "x": 258.5599888392857,
                    "y": 571.9771763392857
                }
            ]
        }
    ],
    "version": "2.2.0"
}